compas_robots/__init__.py
compas_robots/configuration.py
compas_robots/blender/__init__.py
compas_robots/blender/scene/__init__.py
compas_robots/blender/scene/robotmodelobject.py
compas_robots/data/ur_description/meshes/ur5/collision/base.stl
compas_robots/data/ur_description/meshes/ur5/collision/forearm.stl
compas_robots/data/ur_description/meshes/ur5/collision/shoulder.stl
compas_robots/data/ur_description/meshes/ur5/collision/upperarm.stl
compas_robots/data/ur_description/meshes/ur5/collision/wrist1.stl
compas_robots/data/ur_description/meshes/ur5/collision/wrist2.stl
compas_robots/data/ur_description/meshes/ur5/collision/wrist3.stl
compas_robots/data/ur_description/meshes/ur5/visual/base.obj
compas_robots/data/ur_description/meshes/ur5/visual/forearm.obj
compas_robots/data/ur_description/meshes/ur5/visual/shoulder.obj
compas_robots/data/ur_description/meshes/ur5/visual/upperarm.obj
compas_robots/data/ur_description/meshes/ur5/visual/wrist1.obj
compas_robots/data/ur_description/meshes/ur5/visual/wrist2.obj
compas_robots/data/ur_description/meshes/ur5/visual/wrist3.obj
compas_robots/data/ur_description/urdf/ur5.urdf
compas_robots/files/__init__.py
compas_robots/files/urdf.py
compas_robots/ghpython/__init__.py
compas_robots/ghpython/scene/__init__.py
compas_robots/ghpython/scene/robotmodelobject.py
compas_robots/model/__init__.py
compas_robots/model/base.py
compas_robots/model/geometry.py
compas_robots/model/joint.py
compas_robots/model/link.py
compas_robots/model/robot.py
compas_robots/model/tool.py
compas_robots/resources/__init__.py
compas_robots/resources/basic.py
compas_robots/resources/github.py
compas_robots/resources/mesh_importer.py
compas_robots/rhino/__init__.py
compas_robots/rhino/install.py
compas_robots/rhino/scene/__init__.py
compas_robots/rhino/scene/robotmodelobject.py
compas_robots/scene/__init__.py
compas_robots/scene/baserobotmodelobject.py
compas_robots/viewer/__init__.py
compas_robots/viewer/scene/__init__.py
compas_robots-0.6.0.dist-info/AUTHORS.md
compas_robots-0.6.0.dist-info/LICENSE
compas_robots-0.6.0.dist-info/METADATA
compas_robots-0.6.0.dist-info/WHEEL
compas_robots-0.6.0.dist-info/top_level.txt
compas_robots-0.6.0.dist-info/RECORD
